django_six.py
django_six-1.0.4.dist-info/DESCRIPTION.rst
django_six-1.0.4.dist-info/METADATA
django_six-1.0.4.dist-info/RECORD
django_six-1.0.4.dist-info/WHEEL
django_six-1.0.4.dist-info/metadata.json
django_six-1.0.4.dist-info/top_level.txt
